LocalDataStorage/__init__.py
LocalDataStorage/main.py
LocalDataStorage-0.1.dist-info/LICENSE.txt
LocalDataStorage-0.1.dist-info/METADATA
LocalDataStorage-0.1.dist-info/WHEEL
LocalDataStorage-0.1.dist-info/top_level.txt
LocalDataStorage-0.1.dist-info/RECORD
