Metadata-Version: 2.1
Name: LocalDataStorage
Version: 0.1
Summary: This Python package creates a file locally in the user's device more easily.
Author: Samar Panchal
Author-email: 123samarpanchal@gmail.com
Classifier: Programming Language :: Python :: 3
Classifier: License :: OSI Approved :: MIT License
Classifier: Operating System :: OS Independent
Requires-Python: >=3.6
License-File: LICENSE.txt
